{"root":{"directories":{"Project":{"directories":{"ResidentAppModule":{"directories":{"src":{"directories":{"main":{"directories":{"java":{"directories":{"console":{"directories":{"commands":{"directories":{},"files":{"ManualException.java":1654800329226,"FindCommand.java":1654800329226,"FetchCommand.java":1654800329225,"SyncCommand.java":1654800329227,"ConnectCommand.java":1654825759427,"Command.java":1654800329222,"ActionCommand.java":1654800329221,"ExitCommand.java":1654806265751,"ConnectedCommand.java":1654823786754,"DeleteCommand.java":1654800329224}}},"files":{"ConsoleInterface.java":1654806307801}},"george":{"directories":{"resident":{"directories":{"tree":{"directories":{"actions":{"directories":{},"files":{"PushDeal.java":1654829047086,"TreeDeal.java":1654800329242,"TreeActionsEnum.java":1654800329241,"DeleteDeal.java":1654825659980}}},"files":{"TreeDirectory.java":1654800329237,"WildcardTreeDirectory.java":1654800329238,"FileSystemTree.java":1654800329237}},"sync":{"directories":{},"files":{"Device.java":1654800329233,"ActionHandler.java":1654830763556,"UpcomingFileThread.java":1654829846784,"PeerManager.java":1654800329234,"ConnectivityResident.java":1654820800638}},"exceptions":{"directories":{},"files":{"BadSyncDirectory.java":1654800329230,"DeviceNotFound.java":1654800329231}}},"files":{"SynchronizedDirectory.java":1654820800601}}},"files":{"FileListener.java":1654800329228,"testingListener.java":1654800329243,"ListenerThread.java":1654800329228}}},"files":{}}},"files":{}}},"files":{}},".idea":{"directories":{"codeStyles":{"directories":{},"files":{"Project.xml":1654800329213,"codeStyleConfig.xml":1654800329214}}},"files":{"misc.xml":1654800329217,".gitignore":1654800329213,"vcs.xml":1654800329217,"compiler.xml":1654800329215,"jarRepositories.xml":1654800329216}},"target":{"directories":{"classes":{"directories":{"console":{"directories":{"commands":{"directories":{},"files":{"SyncCommand.class":1654828644665,"FetchCommand.class":1654828644651,"DeleteCommand.class":1654828644643,"FindCommand.class":1654828644660,"ExitCommand.class":1654828644646,"ManualException.class":1654828644451,"ConnectedCommand.class":1654828644638,"ActionCommand.class":1654828644358,"Command.class":1654828644365,"ConnectCommand.class":1654828644628}}},"files":{"ConsoleInterface.class":1654828644721}},"george":{"directories":{"resident":{"directories":{"tree":{"directories":{"actions":{"directories":{},"files":{"PushDeal.class":1654829849238,"DeleteDeal.class":1654828644769,"TreeActionsEnum.class":1654828644506,"TreeDeal.class":1654828644771}}},"files":{"WildcardTreeDirectory.class":1654828644783,"TreeDirectory.class":1654828644617,"FileSystemTree.class":1654828644607}},"sync":{"directories":{},"files":{"ActionHandler$1.class":1654830766034,"ConnectivityResident.class":1654828644443,"Device.class":1654828644517,"ActionHandler.class":1654830766051,"PeerManager.class":1654828644578,"UpcomingFileThread.class":1654829849416}},"exceptions":{"directories":{},"files":{"DeviceNotFound.class":1654828644370,"BadSyncDirectory.class":1654828644496}}},"files":{"SynchronizedDirectory.class":1654828644600}}},"files":{"ListenerThread.class":1654828644757,"FileListener.class":1654828644725,"testingListener.class":1654828644786}}},"files":{}},"generated-sources":{"directories":{"annotations":{"directories":{},"files":{}}},"files":{}}},"files":{}}},"files":{"pom.xml":1654800329218}},"ConnectivityModule":{"directories":{"src":{"directories":{"main":{"directories":{"java":{"directories":{"connectivity":{"directories":{"broadcast":{"directories":{},"files":{"BroadcastReceiver.java":1654800329200,"Broadcast.java":1654800329199,"BroadcastSender.java":1654800329201}},"connection":{"directories":{},"files":{"LocalConnection.java":1654826020770,"ConnectionsManager.java":1654823201265,"ConnectionReceiver.java":1654824519333,"Connection.java":1654826037400,"ConnectionSender.java":1654824519305}},"exceptions":{"directories":{},"files":{"DeviceAlreadyConnectedException.java":1654800329208,"DeviceConnectException.java":1654800329209,"BroadcastFailedException.java":1654800329207,"DeviceDisconnectedException.java":1654800329210,"HandshakeException.java":1654800329210}}},"files":{"Peer.java":1654827930438}}},"files":{}},"resources":{"directories":{},"files":{"message.txt":1654800329211}}},"files":{}}},"files":{}},".idea":{"directories":{},"files":{"misc.xml":1654800329175,"modules.xml":1654800329175,"workspace.xml":1654800329195,".gitignore":1654800329173,"vcs.xml":1654800329194,"uiDesigner.xml":1654800329194,"compiler.xml":1654800329173,"jarRepositories.xml":1654800329174}},"target":{"directories":{"classes":{"directories":{"connectivity":{"directories":{"broadcast":{"directories":{},"files":{"BroadcastReceiver.class":1654828593104,"Broadcast.class":1654828593032,"BroadcastSender.class":1654828593060}},"connection":{"directories":{},"files":{"ConnectionSender.class":1654828593146,"ConnectionsManager.class":1654828593170,"LocalConnection.class":1654828593472,"Connection.class":1654828593112,"ConnectionReceiver.class":1654828593132}},"exceptions":{"directories":{},"files":{"DeviceAlreadyConnectedException.class":1654828593188,"DeviceDisconnectedException.class":1654828593196,"HandshakeException.class":1654828593200,"BroadcastFailedException.class":1654828593065,"DeviceConnectException.class":1654828593191}}},"files":{"Peer.class":1654828593226}}},"files":{"message.txt":1654800329211}},"generated-sources":{"directories":{"annotations":{"directories":{},"files":{}}},"files":{}}},"files":{}}},"files":{"pom.xml":1654800329196}},"UIModule":{"directories":{"src":{"directories":{"main":{"directories":{"java":{"directories":{"com":{"directories":{"SettingsPage":{"directories":{},"files":{"MyButton.java":1654800329266,"DrawRoundRectangle.java":1654800329265,"SettingsPage.java":1654800329267,"RoundedRectBorder.java":1654800329267}},"FirstPage":{"directories":{},"files":{"TextFieldWithPrompt.java":1654800329261,"FirstPagePanel.java":1654800329258,"RoundedButton.java":1654800329261,"Main.java":1654800329259,"PortValidator.java":1654800329260,"FirstPageContentPanel.java":1654800329257}},"ConnectionPage":{"directories":{"example":{"directories":{},"files":{"Main.java":1654800329255}}},"files":{"MyButton.java":1654800329254,"DrawRoundRectangle.java":1654800329253,"RoundedRectBorder.java":1654800329254,"ConPage.java":1654800329251}},"FilePage":{"directories":{},"files":{"FilePage.java":1654800329256}},"SyncPage":{"directories":{},"files":{"SyncPage.java":1654800329272,"MyButton.java":1654800329270,"DrawRoundRectangle.java":1654800329269,"RoundedRectBorder.java":1654800329271}},"menu":{"directories":{},"files":{"RoundedButton.java":1654800329275,"Main.java":1654800329273,"MainMenu.java":1654800329274}},"MainFrame":{"directories":{},"files":{"MainFrame.java":1654819119647}},"misc":{"directories":{},"files":{"CustomTableModel.java":1654800329276,"DataController.java":1654800329277}}},"files":{"Main.java":1654800329263}}},"files":{"fisier":1654800329277}}},"files":{}}},"files":{}},".idea":{"directories":{},"files":{"misc.xml":1654800329247,".name":1654800329245,".gitignore":1654800329244,"vcs.xml":1654800329248,"uiDesigner.xml":1654800329247,"compiler.xml":1654800329246,"jarRepositories.xml":1654800329246}}},"files":{"pom.xml":1654800329249}},".idea":{"directories":{"inspectionProfiles":{"directories":{},"files":{"Project_Default.xml":1654800329167}},"codeStyles":{"directories":{},"files":{"Project.xml":1654800329165,"codeStyleConfig.xml":1654800329166}}},"files":{"misc.xml":1654800329168,".name":1654800329164,"workspace.xml":1654831385422,".gitignore":1654800329163,"vcs.xml":1654800329169,"uiDesigner.xml":1654800329169,"compiler.xml":1654800329166,"jarRepositories.xml":1654800329168}},".peer":{"directories":{},"files":{}}},"files":{"Connectivity.iml":1654800329170,"ConnectivityModule.iml":1654800329171,"pom.xml":1654800329278}},".git":{"directories":{"refs":{"directories":{"remotes":{"directories":{"origin":{"directories":{},"files":{"HEAD":1654800329141,"george":1654828399945}}},"files":{}},"heads":{"directories":{},"files":{"george":1654828395327}},"tags":{"directories":{},"files":{}}},"files":{}},"objects":{"directories":{"22":{"directories":{},"files":{"1bb1d65e852c1958dff2613966cb13e983a058":1654828380967}},"88":{"directories":{},"files":{"6017dd7359e9ffa45be2d9c283f41a5887ec8a":1654828380959}},"01":{"directories":{},"files":{"468f932d06e56f2779d9c7baf13b2c39536c42":1654828395312}},"24":{"directories":{},"files":{"bbb5ba89b7d632782967694e5ce628cdb411ca":1654828395308}},"48":{"directories":{},"files":{"db3710a15b8f1578d23168175e810280ebdf3b":1654805839717}},"9c":{"directories":{},"files":{"30c2ad12cfffadc44ef69cb25d9607bb793728":1654828380973}},"f2":{"directories":{},"files":{"eea294c8c7ee08ba213e8bf4f7a16624f15723":1654828395276}},"5b":{"directories":{},"files":{"59bcbcdf21e16ba672ace12b2f68868163b4b6":1654828395288}},"7d":{"directories":{},"files":{"4614448fc4cf9cff1da6507ce4ba7775ef3cb1":1654828395274}},"d1":{"directories":{},"files":{"40fd9ce8d69fa3c312d784aee7a9a65729bc9e":1654828380978,"a742d0871bfd12314da6ab9cd2196ba5e328e2":1654828380989}},"7f":{"directories":{},"files":{"1729c123727615ea53b28b4d3bebfac16bab38":1654828395316}},"1a":{"directories":{},"files":{"41bf153265a308bf3596639e92483b193687fa":1654828380945}},"3c":{"directories":{},"files":{"8ae2d89f325a6d2786176cc0ca2ab21e8389d5":1654828395278}},"b2":{"directories":{},"files":{"502553149697f4faca72c15cd4049b4a8389c6":1654828395314}},"1b":{"directories":{},"files":{"e0fdb3247f17e69ffe0cbff8bcc93b72c14a35":1654828395290}},"b3":{"directories":{},"files":{"d56088fae67930bdf49d9b69cb5a59a0604a7c":1654828395294}},"b8":{"directories":{},"files":{"9e3cc194579824825a4d0c1ed4bd72b536fd8b":1654828395310}},"72":{"directories":{},"files":{"7ed80e8af71f1b808365ba242fc85b83142ccc":1654828395318}},"95":{"directories":{},"files":{"9a0cbf4f00267d86859033abdf590e9dadbca1":1654828380957}},"75":{"directories":{},"files":{"428c1784c395041df1fb66cdf499f18335b1cd":1654828395292}},"10":{"directories":{},"files":{"89e50cdbf90219ff2eea0e20ef488862967e79":1654828395280}},"76":{"directories":{},"files":{"a98e730ff28f744a50983337bb008476e188a3":1654828395267}},"info":{"directories":{},"files":{}},"11":{"directories":{},"files":{"01f63826031963fe901911c41e7da70e32787c":1654828380948}},"aa":{"directories":{},"files":{"a1f1bd501f37843f936a3a01aaddd490ee25da":1654828395282,"f5952e7df7468204ec209ef57bc90f209fdd1f":1654828380980}},"56":{"directories":{},"files":{"b686443196935f274a1c0fa4338be6a1840fdb":1654828380965}},"78":{"directories":{},"files":{"cb857f61f71041300420edd64f2a2d00910b16":1654828380984}},"18":{"directories":{},"files":{"016ea6912be692f28a33894eb67f598898da3d":1654828395286}},"8b":{"directories":{},"files":{"5a92b6ac9cf7ded98599ededa7c841bb04afa3":1654828395303}},"6a":{"directories":{},"files":{"79e6def87e5b01593ba2ccc11962bdc0b6b145":1654828395296}},"c0":{"directories":{},"files":{"8a2a48a65092222e06e596b087f39e78bdc58f":1654828380982}},"pack":{"directories":{},"files":{"pack-3e48c264b0078c7669186b9fa8c2836e1c5f2b5a.idx":1654800327946,"pack-3e48c264b0078c7669186b9fa8c2836e1c5f2b5a.pack":1654800327944}},"6f":{"directories":{},"files":{"8411fb6668428e46b5069f178ec1be73f263dd":1654828380962}},"c4":{"directories":{},"files":{"bab8e1e9194e128661816a02de4814e253f11d":1654828395305}},"c5":{"directories":{},"files":{"023be9cec6e5ec0abeece97b101dd9d25d1ee6":1654828395323}},"2e":{"directories":{},"files":{"dcfcefef58e012d8bcb04c772d95df9403cf22":1654828395298}},"c8":{"directories":{},"files":{"c5891410e97c8653160bc95810376375df6265":1654828395272}},"0f":{"directories":{},"files":{"5e35e60f4ad1b633aaee360a14d8fbbc1f01bb":1654828380954}},"a7":{"directories":{},"files":{"02a246ac53fecc418b49e0b8d4db6c23bdfb05":1654828380993}},"c9":{"directories":{},"files":{"7d5cbc17633d0fdb108df5f64574407ae3479d":1654828395269}},"60":{"directories":{},"files":{"86e698f5dba7e0a6cc68759f0520e32488a13f":1654828380951}},"61":{"directories":{},"files":{"0a85a504fcb5af1138f5d4e1258e6f487e0e9f":1654828395300}},"83":{"directories":{},"files":{"83a2eff7eeb052e0795fc9f1dffa68aa16c837":1654828395264}},"40":{"directories":{},"files":{"5aa5f99f01c0b46b8350bad090a2ae4c0af17a":1654828380971}},"da":{"directories":{},"files":{"01e8239e7077c48cefe378fe0d40a5bfb69cde":1654828380976}},"fe":{"directories":{},"files":{"fbd157da5693b57af622977f124e3dafd3f0c9":1654828395284}}},"files":{}},"hooks":{"directories":{},"files":{"prepare-commit-msg.sample":1654800320966,"applypatch-msg.sample":1654800320893,"fsmonitor-watchman.sample":1654800320914,"update.sample":1654800320984,"post-update.sample":1654800320915,"push-to-checkout.sample":1654800320976,"commit-msg.sample":1654800320898,"pre-applypatch.sample":1654800320916,"pre-rebase.sample":1654800320951,"pre-commit.sample":1654800320929,"pre-merge-commit.sample":1654800320930,"pre-push.sample":1654800320936,"pre-receive.sample":1654800320951}},"logs":{"directories":{"refs":{"directories":{"remotes":{"directories":{"origin":{"directories":{},"files":{"HEAD":1654800329141,"george":1654828399950}}},"files":{}},"heads":{"directories":{},"files":{"george":1654828395327}}},"files":{}}},"files":{"HEAD":1654828395327}},"info":{"directories":{},"files":{"exclude":1654800320985}}},"files":{"HEAD":1654800329143,"COMMIT_EDITMSG":1654828395322,"packed-refs":1654800329132,"description":1654800320884,"index":1654828395319,"config":1654800329153}},".idea":{"directories":{},"files":{"misc.xml":1654800329161,"IPProjectB2.iml":1654800329158,"modules.xml":1654800329162,".gitignore":1654800329158,"vcs.xml":1654800329162,"compiler.xml":1654800329159,"jarRepositories.xml":1654800329161,"discord.xml":1654800329160}},".peer":{"directories":{},"files":{"action2015198534404014049.json":1654825008077,"action14528574662326489337.json":1654823886347,"action4979001871524485811.json":1654828341745,"action651179889744767953.json":1654827180042,"action8841969365965840921.json":1654831440188,"action17366589355690356827.json":1654801932448,"action3717927874765213243.json":1654829796068,"action704277511439883056.json":1654821383629}}},"files":{".gitignore":1654800329157}},"action":"Fetch","path":""}